{
  "resourceType": "Bundle",
  "id": "act-lactating__act-avgrisk",
  "type": "collection",
  "entry": [
    {
      "resource": {
        "resourceType": "Patient",
        "id": "defaultPatient",
        "name": [
          {
            "given": [
              "Jane"
            ],
            "family": "Doe"
          }
        ],
        "gender": "female",
        "birthDate": "1981-01-01"
      }
    },
    {
      "resource": {
        "resourceType": "Observation",
        "id": "9e2fd317-58b5-4681-b4b3-57d61be7d761",
        "subject": {
          "reference": "Patient/defaultPatient"
        },
        "status": "final",
        "code": {
          "coding": [
            {
              "system": "http://cancerscreeningcds.github.io/bcsm-cds/CodeSystem/screening-observation-code-system",
              "code": "currentlylactating",
              "display": "Currently lactating"
            }
          ]
        },
        "valueBoolean": true,
        "effectiveDateTime": "2024-12-10T00:00:00.0Z"
      }
    }
  ]
}