{
  "resourceType": "Bundle",
  "id": "eve-atypicalbxpop_eve-ageAny_act-HighRiskReferral_act-estlifexpectancy",
  "type": "collection",
  "entry": [
    {
      "resource": {
        "resourceType": "Patient",
        "id": "defaultPatient",
        "name": [
          {
            "given": [
              "Jane"
            ],
            "family": "Doe"
          }
        ],
        "gender": "female",
        "birthDate": "1980-01-01"
      }
    },
    {
      "resource": {
        "resourceType": "Condition",
        "id": "77f774d5-0728-48be-b5fc-aa1570a1f06c",
        "subject": {
          "reference": "Patient/defaultPatient"
        },
        "clinicalStatus": {
          "coding": [
            {
              "system": "http://terminology.hl7.org/CodeSystem/condition-clinical",
              "code": "active",
              "display": "Active"
            }
          ]
        },
        "verificationStatus": {
          "coding": [
            {
              "system": "http://terminology.hl7.org/CodeSystem/condition-ver-status",
              "code": "confirmed",
              "display": "Confirmed"
            }
          ]
        },
        "code": {
          "coding": [
            {
              "system": "http://snomed.info/sct",
              "code": "62061000119107"
            }
          ]
        }
      }
    }
  ]
}